GPy_ABCD/__init__.py
GPy_ABCD/config.py
GPy_ABCD/KernelExpansion/__init__.py
GPy_ABCD/KernelExpansion/grammar.py
GPy_ABCD/KernelExpansion/kernelExpressionOperations.py
GPy_ABCD/KernelExpansion/kernelInterpretation.py
GPy_ABCD/KernelExpansion/kernelOperations.py
GPy_ABCD/KernelExpressions/__init__.py
GPy_ABCD/KernelExpressions/all.py
GPy_ABCD/KernelExpressions/base.py
GPy_ABCD/KernelExpressions/change.py
GPy_ABCD/KernelExpressions/commutative_base.py
GPy_ABCD/KernelExpressions/commutatives.py
GPy_ABCD/Kernels/__init__.py
GPy_ABCD/Kernels/baseKernels.py
GPy_ABCD/Kernels/changeOperators.py
GPy_ABCD/Kernels/changeWindowShiftedSides.py
GPy_ABCD/Kernels/changeWindowThreePart.py
GPy_ABCD/Kernels/linearKernel.py
GPy_ABCD/Kernels/linearOffsetKernel.py
GPy_ABCD/Kernels/periodicKernel.py
GPy_ABCD/Kernels/sigmoidalKernels.py
GPy_ABCD/Models/__init__.py
GPy_ABCD/Models/model.py
GPy_ABCD/Models/modelSearch.py
GPy_ABCD/Util/__init__.py
GPy_ABCD/Util/benchmarking.py
GPy_ABCD/Util/dataAndPlottingUtil.py
GPy_ABCD/Util/genericUtil.py
GPy_ABCD/Util/kernelUtil.py
GPy_ABCD/Util/modelUtil.py
GPy_ABCD/Util/numba_types.py
GPy_ABCD/Util/showcaseAllKernels.py
GPy_ABCD-1.2.3.dist-info/LICENSE
GPy_ABCD-1.2.3.dist-info/METADATA
GPy_ABCD-1.2.3.dist-info/WHEEL
GPy_ABCD-1.2.3.dist-info/top_level.txt
GPy_ABCD-1.2.3.dist-info/RECORD
