Metadata-Version: 2.1
Name: GPy-ABCD
Version: 1.2.3
Summary: Basic implementation with GPy of an Automatic Bayesian Covariance Discovery (ABCD) system
Home-page: https://github.com/T-Flet/GPy-ABCD
Author: Thomas Fletcher
Author-email: T-Fletcher@outlook.com
License: BSD 3-Clause
Classifier: Development Status :: 4 - Beta
Classifier: Programming Language :: Python
Classifier: Programming Language :: Python :: 3.8
Classifier: Programming Language :: Python :: 3.9
Classifier: Programming Language :: Python :: 3.10
Classifier: Programming Language :: Python :: 3.11
Classifier: Programming Language :: Python :: 3.12
License-File: LICENSE
Requires-Dist: numpy ==1.23.5
Requires-Dist: numba >=0.55.2
Requires-Dist: GPy >=1.12.0
Requires-Dist: scipy >=1.6.2
Requires-Dist: pandas >=1.2.4
Requires-Dist: matplotlib >=3.3.2
Requires-Dist: plotnine >=0.7.1
